[
  {
    "question": "以下关于二分图的描述，哪一项是正确的？",
    "options": [
      "二分图中所有顶点都在同一个集合中",
      "二分图的顶点可以划分为两个不相交集合，且同一集合内的顶点之间没有边",
      "二分图必须是有向图",
      "二分图中不能存在环"
    ],
    "answer": 1,
    "explanation": "二分图（Bipartite Graph）的定义是：顶点集可以划分为两个不相交的子集 U 和 V，使得每条边的两个端点分别属于 U 和 V。也就是说，同一集合内的顶点之间没有边相连。二分图可以是有向或无向的，也可以包含偶数长度的环，但不能包含奇数长度的环。"
  },
  {
    "question": "使用 BFS 染色法判断一个图是否为二分图，时间复杂度是多少？",
    "options": [
      "O(V)",
      "O(E)",
      "O(V + E)",
      "O(V × E)"
    ],
    "answer": 2,
    "explanation": "BFS 染色法需要遍历图中的所有顶点和边：每个顶点入队出队一次 O(V)，每条边被检查一次 O(E)，因此总时间复杂度为 O(V + E)。空间复杂度为 O(V)，用于存储颜色数组和队列。"
  },
  {
    "question": "二分图的最大匹配问题中，增广路径（Augmenting Path）的含义是什么？",
    "options": [
      "从任意顶点出发到达任意顶点的最短路径",
      "一条交替经过匹配边和非匹配边的路径，且两端都是未匹配顶点",
      "一条包含所有顶点的哈密顿路径",
      "一条权重最小的路径"
    ],
    "answer": 1,
    "explanation": "增广路径是从一个未匹配顶点出发，到另一个未匹配顶点结束的路径，路径上的边交替为非匹配边和匹配边。沿着增广路径翻转匹配状态（非匹配边变匹配边，匹配边变非匹配边），可以使匹配数增加 1。这是匈牙利算法的核心思想。"
  },
  {
    "question": "匈牙利算法求解二分图最大匹配的时间复杂度是多少？",
    "options": [
      "O(V + E)",
      "O(V²)",
      "O(V × E)",
      "O(V³)"
    ],
    "answer": 2,
    "explanation": "匈牙利算法对每个未匹配的顶点尝试寻找增广路径。每次 DFS 寻找增广路径的时间为 O(E)，最多进行 O(V) 次尝试，因此总时间复杂度为 O(V × E)。在稠密图中 E 接近 V²，复杂度退化为 O(V³)。"
  },
  {
    "question": "König 定理描述了二分图中哪两个量的等价关系？",
    "options": [
      "最大匹配数等于最小点覆盖数",
      "最大独立集等于最小边覆盖数",
      "最大流等于最小割",
      "顶点数等于边数加一"
    ],
    "answer": 0,
    "explanation": "König 定理（König's Theorem）指出：在二分图中，最大匹配的边数等于最小点覆盖的顶点数。这是二分图的一个经典性质，也是匈牙利算法的理论基础之一。该定理还等价于：最大独立集的大小 = 顶点数 - 最大匹配数。"
  }
]
