[
  {
    "question": "Graham Scan 算法的时间复杂度是多少？",
    "options": ["O(n)", "O(n log n)", "O(n²)", "O(n² log n)"],
    "answer": 1,
    "explanation": "Graham Scan 需要先对所有点按极角排序，排序的时间复杂度为 O(n log n)。排序后每个点最多入栈和出栈各一次，扫描过程为 O(n)。因此总时间复杂度为 O(n log n)。"
  },
  {
    "question": "在 Graham Scan 中，如何判断三个点是否构成「左转」？",
    "options": [
      "计算两点之间的距离",
      "计算叉积（向量积）并判断符号",
      "计算三点构成的角度",
      "比较三个点的 x 坐标"
    ],
    "answer": 1,
    "explanation": "判断三点 P1、P2、P3 是否左转，计算向量 P1P2 与 P1P3 的叉积 (P2-P1) x (P3-P1)。若叉积 > 0 则为左转（逆时针），叉积 < 0 则为右转（顺时针），叉积 = 0 则三点共线。"
  },
  {
    "question": "Andrew 单调链算法与 Graham Scan 相比，主要优势是什么？",
    "options": [
      "时间复杂度更低",
      "不需要使用栈",
      "不需要计算极角，避免浮点误差",
      "可以处理三维凸包"
    ],
    "answer": 2,
    "explanation": "Andrew 单调链按 x 坐标（x 相同时按 y）排序，然后分别从左到右构建下凸壳和从右到左构建上凸壳。它只需要比较坐标和叉积，完全使用整数运算，避免了 Graham Scan 中计算极角时可能产生的浮点精度问题。"
  },
  {
    "question": "旋转卡壳（Rotating Calipers）算法常用于凸包的什么问题？",
    "options": [
      "求凸包面积",
      "求凸包直径（最远点对）",
      "判断点是否在凸包内",
      "求凸包周长"
    ],
    "answer": 1,
    "explanation": "旋转卡壳是一种利用凸包对踵点（antipodal points）的技术，最经典的应用是求凸包的直径——即凸包上距离最远的两个点。其核心思想是用一对平行线「夹住」凸包，旋转这对线来遍历所有对踵点对，时间复杂度为 O(n)。"
  },
  {
    "question": "给定 n 个点，凸包上最多有多少个顶点？",
    "options": ["n/2", "n-1", "n", "2n"],
    "answer": 2,
    "explanation": "在最坏情况下，n 个点可能全部在凸包上（例如所有点恰好在一个圆上均匀分布），因此凸包上最多有 n 个顶点。这也是为什么凸包算法的时间复杂度下界为 O(n log n)——因为输出规模可能达到 O(n)，且排序需要 O(n log n)。"
  }
]
